vboxwebber/VirtualBox_constants.py
vboxwebber/__init__.py
vboxwebber-0.1.0.dist-info/LICENSE
vboxwebber-0.1.0.dist-info/METADATA
vboxwebber-0.1.0.dist-info/WHEEL
vboxwebber-0.1.0.dist-info/top_level.txt
vboxwebber-0.1.0.dist-info/RECORD
