Metadata-Version: 2.1
Name: vboxwebber
Version: 0.1.0
Summary: A standalone client for VirtualBox webservice API
Home-page: https://github.com/larshson/vboxwebber
Author: larshson
Author-email: larshson@gmail.com
License: UNKNOWN
Platform: UNKNOWN
Classifier: Development Status :: 3 - Alpha
Classifier: Programming Language :: Python
Classifier: License :: OSI Approved :: GNU General Public License v2 (GPLv2)
Classifier: Operating System :: OS Independent
Requires-Python: >=2.7
Requires-Dist: zeep
